jupyterlab_google_analytics/__init__.py
jupyterlab_google_analytics/_version.py
jupyterlab_google_analytics-1.2.0.data/data/share/jupyter/labextensions/jupyterlab-google-analytics/package.json
jupyterlab_google_analytics-1.2.0.data/data/share/jupyter/labextensions/jupyterlab-google-analytics/schemas/jupyterlab-google-analytics/package.json.orig
jupyterlab_google_analytics-1.2.0.data/data/share/jupyter/labextensions/jupyterlab-google-analytics/schemas/jupyterlab-google-analytics/plugin.json
jupyterlab_google_analytics-1.2.0.data/data/share/jupyter/labextensions/jupyterlab-google-analytics/static/568.a1c4bc17315405732ac0.js
jupyterlab_google_analytics-1.2.0.data/data/share/jupyter/labextensions/jupyterlab-google-analytics/static/747.b74722fbcf9a288107c4.js
jupyterlab_google_analytics-1.2.0.data/data/share/jupyter/labextensions/jupyterlab-google-analytics/static/remoteEntry.670e4ab91cd9d481398e.js
jupyterlab_google_analytics-1.2.0.data/data/share/jupyter/labextensions/jupyterlab-google-analytics/static/style.js
jupyterlab_google_analytics-1.2.0.data/data/share/jupyter/labextensions/jupyterlab-google-analytics/static/third-party-licenses.json
jupyterlab_google_analytics-1.2.0.data/data/share/jupyter/labextensions/jupyterlab-google-analytics/install.json
jupyterlab_google_analytics-1.2.0.dist-info/METADATA
jupyterlab_google_analytics-1.2.0.dist-info/WHEEL
jupyterlab_google_analytics-1.2.0.dist-info/licenses/LICENSE
jupyterlab_google_analytics-1.2.0.dist-info/RECORD
