Metadata-Version: 2.1
Name: jupyterlab_google_analytics
Version: 1.2.0
Summary: A JupyterLab extension.
Project-URL: Homepage, https://github.com/team-monolith-product/jupyterlab-google-analytics
Project-URL: Bug Tracker, https://github.com/team-monolith-product/jupyterlab-google-analytics/issues
Project-URL: Repository, https://github.com/team-monolith-product/jupyterlab-google-analytics.git
Author-email: ChangHwan Lee <lch@team-mono.com>
License: BSD 3-Clause License
License-File: LICENSE
Classifier: Framework :: Jupyter
Classifier: Framework :: Jupyter :: JupyterLab
Classifier: Framework :: Jupyter :: JupyterLab :: 4
Classifier: Framework :: Jupyter :: JupyterLab :: Extensions
Classifier: Framework :: Jupyter :: JupyterLab :: Extensions :: Prebuilt
Classifier: License :: OSI Approved :: BSD License
Classifier: Programming Language :: Python
Classifier: Programming Language :: Python :: 3
Classifier: Programming Language :: Python :: 3.8
Classifier: Programming Language :: Python :: 3.9
Classifier: Programming Language :: Python :: 3.10
Classifier: Programming Language :: Python :: 3.11
Classifier: Programming Language :: Python :: 3.12
Requires-Python: >=3.8
